rustxes-0.2.10.dist-info/METADATA
rustxes-0.2.10.dist-info/WHEEL
rustxes-0.2.10.dist-info/licenses/LICENSE-APACHE
rustxes-0.2.10.dist-info/licenses/LICENSE-MIT
rustxes/__init__.py
rustxes/export_xes.py
rustxes/import_ocel.py
rustxes/import_xes.py
rustxes/rustxes.cpython-39-darwin.so
rustxes-0.2.10.dist-info/RECORD
