Metadata-Version: 2.4
Name: rustxes
Version: 0.2.10
Classifier: Programming Language :: Rust
Classifier: Programming Language :: Python :: Implementation :: CPython
Classifier: Programming Language :: Python :: Implementation :: PyPy
Requires-Dist: polars[pandas,pyarrow]
License-File: LICENSE-APACHE
License-File: LICENSE-MIT
Summary: Rust-based XES/OCEL2 event log importer
Requires-Python: >=3.7
